parse2csv/__init__.py
parse2csv/cli.py
parse2csv/parse2csv.py
parse2csv/reduct.py
parse2csv/release.py
parse2csv-0.1.5.dist-info/LICENSE
parse2csv-0.1.5.dist-info/METADATA
parse2csv-0.1.5.dist-info/WHEEL
parse2csv-0.1.5.dist-info/entry_points.txt
parse2csv-0.1.5.dist-info/top_level.txt
parse2csv-0.1.5.dist-info/RECORD
