Metadata-Version: 2.1
Name: parse2csv
Version: 0.1.5
Summary: A command-line tool to parse multiple files for named
Home-page: https://github.com/cartoonist/parse2csv
Author: Ali Ghaffaari
Author-email: ali.ghaffaari@mpi-inf.mpg.de
License: MIT
Download-URL: https://github.com/cartoonist/parse2csv/tarball/0.1.5
Keywords: parse text convert csv comma separated values
Platform: UNKNOWN
Classifier: Development Status :: 2 - Pre-Alpha
Classifier: Environment :: Console
Classifier: License :: OSI Approved :: MIT License
Classifier: Programming Language :: Python :: 2
Classifier: Programming Language :: Python :: 2.7
Classifier: Programming Language :: Python :: 3
Classifier: Programming Language :: Python :: 3.5
Classifier: Programming Language :: Python :: 3.6
Classifier: Intended Audience :: Developers
Classifier: Topic :: Text Processing :: General
License-File: LICENSE
Requires-Dist: click>=6.7
Requires-Dist: parse>=1.8.2
Requires-Dist: PyYAML>=3.12
Provides-Extra: test
Requires-Dist: nose>=1.0; extra == "test"
Requires-Dist: coverage; extra == "test"
